asc2mb/__init__.py
asc2mb/asc2mb.py
asc2mb-0.7.2.dist-info/LICENSE
asc2mb-0.7.2.dist-info/METADATA
asc2mb-0.7.2.dist-info/WHEEL
asc2mb-0.7.2.dist-info/entry_points.txt
asc2mb-0.7.2.dist-info/RECORD
