Metadata-Version: 2.1
Name: asc2mb
Version: 0.7.2
Summary: Manage your timetable by pasing the XML export from asc and format into two files suitable for upload into ManageBac
License: MIT
Keywords: ManageBac,aSc,timetable
Author: Adam Morris
Author-email: adam.morris@fariaedu.com
Requires-Python: >=3.7,<4.0
Classifier: License :: OSI Approved :: MIT License
Classifier: Programming Language :: Python :: 3
Classifier: Programming Language :: Python :: 3.7
Classifier: Programming Language :: Python :: 3.8
Classifier: Programming Language :: Python :: 3.9
Classifier: Programming Language :: Python :: 3.10
Classifier: Programming Language :: Python :: 3.11
Requires-Dist: click (==8.0)
Requires-Dist: lxml (>=4.9.1,<5.0.0)
Requires-Dist: rich (>=13.3.5,<14.0.0)
Requires-Dist: rich-click (>=1.6.1,<2.0.0)
